alens/pricedl/__init__.py
alens/pricedl/config.py
alens/pricedl/direct_dl.py
alens/pricedl/main.py
alens/pricedl/model.py
alens/pricedl/price_flat_file.py
alens/pricedl/quote.py
alens/pricedl/beanprice/__init__.py
alens/pricedl/beanprice/vanguard_au_detail.py
alens/pricedl/beanprice/yahoo.py
alens/pricedl/quotes/__init__.py
alens/pricedl/quotes/ecb.py
alens/pricedl/quotes/fixerio.py
alens/pricedl/quotes/vanguard_au.py
alens/pricedl/quotes/vanguard_au_2023_detail.py
alens/pricedl/quotes/yahoo_finance_downloader.py
alens/pricedl/quotes/yfinance.py
alens/pricedl/quotes/yfinance_downloader.py
alens_pricedl-0.5.7.dist-info/METADATA
alens_pricedl-0.5.7.dist-info/WHEEL
alens_pricedl-0.5.7.dist-info/entry_points.txt
alens_pricedl-0.5.7.dist-info/licenses/LICENSE
alens_pricedl-0.5.7.dist-info/RECORD
