Metadata-Version: 2.4
Name: alens-pricedl
Version: 0.5.7
Summary: Commodity price retrieval, storage, and export in format compatible with Plain-Text Accounting applications.
Project-URL: repository, https://github.com/alensiljak/alens-pricedl
Author: Alen Siljak
License:                     GNU AFFERO GENERAL PUBLIC LICENSE
License-File: LICENSE
Classifier: Development Status :: 3 - Alpha
Classifier: Intended Audience :: Developers
Classifier: License :: OSI Approved :: GNU Affero General Public License v3 or later (AGPLv3+)
Classifier: Operating System :: OS Independent
Classifier: Programming Language :: Python :: 3
Requires-Python: >=3.12
Requires-Dist: asyncclick>=8.1.8
Requires-Dist: beanprice>=2.0.0
Requires-Dist: dotenv>=0.9.9
Requires-Dist: loguru>=0.7.3
Requires-Dist: pyeurofx>=0.6.4
Requires-Dist: requests>=2.32.3
